README.md
setup.py
vcenter_exporter/__init__.py
vcenter_exporter/__main__.py
vcenter_exporter/_py6.py
vcenter_exporter/exporter.py
vcenter_exporter/release.py
vcenter_prometheus_exporter.egg-info/PKG-INFO
vcenter_prometheus_exporter.egg-info/SOURCES.txt
vcenter_prometheus_exporter.egg-info/dependency_links.txt
vcenter_prometheus_exporter.egg-info/entry_points.txt
vcenter_prometheus_exporter.egg-info/requires.txt
vcenter_prometheus_exporter.egg-info/top_level.txt