Metadata-Version: 1.0
Name: vcenter-prometheus-exporter
Version: 0.0.1
Summary: Export prometheus metrics from vcenter host
Home-page: https://github.com/fgouteroux/vcenter_prometheus_exporter.git
Author: Francois Gouteroux
Author-email: francois.gouteroux@gmail.com
License: License :: OSI Approved :: Apache Software License
Keywords: VMWare,VCenter,Prometheus
Platform: UNKNOWN
